{"UpVotes":"3", "WebsiteUrl":"http://twitter.com/otac0n", "Id":"1356", "AccountId":"23210", "CreationDate":"2012-09-26T20:49:37.470", "AboutMe":"<p>I'm a father, a lover, a programmer and a guitarist.<br>\nTwitter: <a href=\"http://twitter.com/otac0n\" rel=\"nofollow\">http://twitter.com/otac0n</a></p>\n\n<p><img src=\"http://stackoverflow.com/users/flair/57986.png\" alt=\"Stack Overflow\"><br>\n<img src=\"http://projecteuler.net/profile/otac0n.png\" alt=\"Project Euler\"></p>\n", "Age":"29", "Location":"Seattle, WA", "DownVotes":"0", "Views":"0", "Reputation":"143", "DisplayName":"John Gietzen", "LastAccessDate":"2012-09-30T18:53:04.890"}