{"OwnerUser":{"UpVotes":"556", "WebsiteUrl":"http://www.markbeadles.com/", "Id":"537", "AccountId":"297827", "CreationDate":"2011-11-27T02:50:39.717", "AboutMe":"<p>Polymathic renaissance redneck</p>\n", "Age":"47", "Location":"Columbus, OH", "DownVotes":"22", "Views":"30", "Reputation":"3876", "DisplayName":"Mark Beadles", "LastAccessDate":"2013-02-02T04:23:30.703"}, "comments":[], "Body":"<p>Using a noun phrase without a determiner is already fairly common in certain registers of English -- <a href=\"http://www.google.com/url?sa=t&amp;rct=j&amp;q=&amp;esrc=s&amp;source=web&amp;cd=6&amp;ved=0CF0QFjAF&amp;url=http://www.media.uoa.gr/lectures/linguistic_archives/mda0405/notes/Bell_Media_and_Language.pdf&amp;ei=oXHjT-PkHMXs2QWWy8XfCw&amp;usg=AFQjCNHZ1QKF7S2gUotL43exWyiNUNa_5w&amp;sig2=sdA0-LB6uwG9zcATklr1Ag\">notably newspaperese</a>.  I think that there you're also more likely to find formal-souding words like <em>said</em> used. </p>\n\n<p>The <a href=\"http://www.oed.com/view/Entry/169800?redirectedFrom=said&amp;\">OED Online gives <em>said</em></a> simply as an adjective (ignoring irrelevant senses) meaning \"<strong>named or mentioned before</strong>\". In the examples they give, <em>said</em> is always used with a preceding determiner.</p>\n\n<p>So I think it's consistent with both of the above to say that:<br>\n(1) <em>said</em> is just an adjective in this case and<br>\n(2) some registers of English allow NPs to occur without Dets more frequently. </p>\n\n<p>thus leading to NPs like \"said children\".  </p>\n", "Id":"2160", "ParentId":"2147", "CreationDate":"2012-06-21T19:14:38.297", "Score":"5", "PostTypeId":"2", "OwnerUserId":"537", "LastActivityDate":"2012-06-21T19:14:38.297", "CommentCount":"17"}