{"OwnerUser":{"UpVotes":"0", "WebsiteUrl":"", "DownVotes":"3", "Id":"2556", "ProfileImageUrl":"https://www.gravatar.com/avatar/?s=128&d=identicon&r=PG&f=1", "AccountId":"3403950", "Views":"9", "Reputation":"738", "CreationDate":"2013-10-07T16:34:15.923", "DisplayName":"fdb", "LastAccessDate":"2014-01-19T01:24:22.827", "AboutMe":""}, "comments":[], "Body":"<p>All of your examples involve compounds (even though the two parts of the compound are in most cases written as separate words). English has inherited from Indo-European the principle that the first part of a compound (Vorderglied) is as a rule not inflected for number or case.</p>\n\n<p>Some of your (implied) German examples are of the same sort: Zebra(streifen), Indianer(reservation) have an uninflected Vorderglied. Others have a Vorderglied in the genitive singular: Kirchen(steuer) follows the old weak declension of Kirche (Kirchen in all cases except nom. sing.), a type also well attested in ancient IE languages.</p>\n", "Id":"4738", "ParentId":"4737", "CreationDate":"2013-10-15T23:46:15.793", "Score":"2", "PostTypeId":"2", "OwnerUserId":"2556", "LastActivityDate":"2013-10-15T23:46:15.793", "CommentCount":"12"}