{"Body":"<p>Are there language-independent aspects of the expression of emotion by intonation? More specifically, are there established relations between the expression of emotion by linguistic intonation and by musical means (i.e. musical intervals/phrases/melodies)? Quick summaries of what is known and/or pointers to the literature would be appreciated. </p>\n", "Id":"240", "LastEditorUserId":"46", "AcceptedAnswerId":"705", "Title":"What is known about the universal aspects of the relation between intonation and emotion?", "CreationDate":"2011-09-17T06:59:23.807", "OwnerUserId":"108", "PostTypeId":"1", "Tags":"<linguistic-universals><intonation><prosody>", "AnswerCount":"1", "comments":[], "LastEditDate":"2011-10-02T01:26:38.073", "LastEditedUser":{"UpVotes":"57", "WebsiteUrl":"http://www.ling.upenn.edu/~ecay/", "Id":"46", "AccountId":"211379", "CreationDate":"2011-09-13T21:05:16.277", "AboutMe":"<p>I am a second-year PhD student in Linguistics at the University of Pennsylvania.  My research interests lie in diachronic syntax, language as an evolutionary system, and quantitative methods in linguistic research.</p>\n", "Age":"26", "Location":"Philadelphia, PA", "DownVotes":"1", "Views":"111", "Reputation":"3004", "DisplayName":"Aaron", "LastAccessDate":"2013-04-30T05:33:49.387"}, "ViewCount":"222", "LastActivityDate":"2011-10-07T18:56:47.027", "Score":"6", "CommentCount":"3", "OwnerUser":{"UpVotes":"8", "DownVotes":"0", "Id":"108", "AccountId":"542522", "Views":"3", "Reputation":"68", "CreationDate":"2011-09-14T08:22:47.957", "DisplayName":"Azo", "LastAccessDate":"2012-08-31T02:49:45.947"}}