{"Body":"<p>I want to develop a program which can differentiate between CVC, VCV, and CV syllable types.</p>\n\n<p>I'm having trouble knowing when vowel has ended in CVC and CV syllables.</p>\n\n<p>I want to read more about it. Are there any websites, papers, or books that would be recommended reading for this task?</p>\n", "Id":"4053", "LastEditorUserId":"51", "Title":"Computationally differentiating between CVC, VCV and CV syllables", "CreationDate":"2013-07-24T07:32:35.877", "OwnerUserId":"2281", "PostTypeId":"1", "Tags":"<phonetics><computational-linguistics><syllables>", "AnswerCount":"1", "comments":[], "LastEditDate":"2013-07-25T06:21:16.253", "LastEditedUser":{"UpVotes":"1436", "WebsiteUrl":"http://en.wiktionary.org/wiki/User:Hippietrail", "ProfileImageUrl":"http://i.stack.imgur.com/ExcaS.jpg", "Id":"51", "AccountId":"250783", "CreationDate":"2011-09-13T21:15:02.967", "AboutMe":"<p>Travelling armchair linguist.</p>\n\n<p>Never studied in an institution but read books and web with probably more breadth than depth.</p>\n\n<p>Always on the road surviving in a strange foreign language, currently Mongolian and Mandarin Chinese.</p>\n\n<p>And I collect dictionaries.</p>\n", "Location":"Beijing, China", "DownVotes":"65", "Views":"221", "Reputation":"4918", "DisplayName":"hippietrail", "LastAccessDate":"2014-01-18T09:27:54.697"}, "ViewCount":"194", "LastActivityDate":"2013-12-22T10:29:02.013", "Score":"0", "CommentCount":"4", "OwnerUser":{"UpVotes":"0", "DownVotes":"0", "Id":"2281", "AccountId":"3086525", "Views":"0", "Reputation":"1", "CreationDate":"2013-07-24T07:32:35.877", "DisplayName":"Meow", "LastAccessDate":"2013-07-24T07:32:35.877"}}