{"Body":"<p>Does anyone know where I can find a comprehensive description of Mandarin Chinese grammar? Like for instance, certain books I could read, or websites I could visit? Suggestions much appreciated! :)</p>\n", "Id":"6444", "ClosedDate":"2014-01-18T14:48:18.257", "Title":"Resource for Mandarin Chinese grammar", "CreationDate":"2014-01-18T06:03:41.663", "OwnerUserId":"1901", "PostTypeId":"1", "Tags":"<grammar><resources><descriptive-linguistics><mandarin>", "comments":[], "ViewCount":"8", "LastActivityDate":"2014-01-18T06:03:41.663", "Score":"0", "CommentCount":"1", "OwnerUser":{"UpVotes":"2", "DownVotes":"0", "ProfileImageUrl":"http://i.stack.imgur.com/vGq9U.jpg", "Id":"1901", "AccountId":"2550250", "Views":"1", "Reputation":"83", "CreationDate":"2013-03-27T03:41:32.680", "DisplayName":"Kaninchen", "LastAccessDate":"2014-01-18T18:14:44.377", "AboutMe":"<p>Ich kann ziemlich gut Deutsch, oder so glaube ich, 和会说一点中文，可是说的不好。Have never formally studied linguistics.</p>\n"}}