{
  "id": "/questions/20887645",
  "creationDate": "2014-01-05T08:51:31.520",
  "body": "\n\nI am writing my app and I want to do the following:\n\nOn the first request, I serve all the client side code (views, models, controllers, css ...) and subsequently I want to do RESTful api calls to the server to populate my app with data.\n\nI've been looking everywhere but can't find a complete example. Connect serves a static directory but after that I don't know how to route RESTful api requests.  ",
  "lastActivityDate": "2014-08-11T05:42:56.220",
  "title": "serving an angular directory and subsequently using restful API's to load data when needed with nodesj",
  "tags": [
    "node.js",
    "api",
    "angularjs",
    "rest",
    "connect"
  ],
  "docScore": 0,
  "comments": [],
  "answers": [],
  "creationYearMonth": "201408",
  "itemTally": 0,
  "owner": {
    "displayName": "user2613541",
    "id": "2613541"
  }
}