{
  "id": "/questions/2444685",
  "creationDate": "2014-03-17T10:08:41.210",
  "body": "\n\nDoes anyone know of any C# syntax highlighter plugins for Confluence? Using the default Java highlighter works, but it misses things like string in C# and String in Java, with the latter being highlighted and the former plain black text. ",
  "lastActivityDate": "2014-11-23T00:37:23.557",
  "title": "C# Syntax Highlighting for Confluence",
  "tags": [
    "c#",
    "java",
    "syntax-highlighting",
    "confluence"
  ],
  "docScore": 0,
  "comments": [],
  "answers": [],
  "creationYearMonth": "201411",
  "itemTally": 0,
  "owner": null
}