{
  "id": "/questions/2446555",
  "creationDate": "2014-03-17T18:58:52.730",
  "body": "\n\nI have got a group of radio buttons that when clicked need to display a corresponding unordered list.  I have got as far as showing the correct list according to which radio button is clicked but cannot figure out how to hide the other lists that need to be hidden.  So if i click the second benefits radion then the second 'spend' ul will display and the other 'spend' uls will hide.\n\nThis is my jQuery:\n\n\t// hide all except first ul\n\t$('div.chevron ul').not(':first').hide();\n\t\n\t//\n\t$('div.chevron > ul > li > input[name=benefits]').live('click',function() { \n\t\n\t    // work out which radio has been clicked\n\t    var $radioClick = $(this).index('div.chevron > ul > li > input[name=benefits]');\n\t    var $radioClick = $radioClick + 1;\n\t\n\t    $('div.chevron > ul').eq($radioClick).show();\n\t\n\t});\n\t\n\t// trigger click event to show spend list\n\tvar $defaultRadio = $('div.chevron > ul > li > input:first[name=benefits]')\n\t$defaultRadio.trigger('click');\n\t\n\nAnd this is my HTML:\n\n\t        <div class=\"divider chevron\">\n\t        <ul>\n\t            <li><strong>What benefit are you most interested in?</strong></li>\n\t            <li>\n\t                <input type=\"radio\" class=\"inlineSpace\" name=\"benefits\" id=\"firstBenefit\" value=\"Dental\" checked=\"checked\" />\n\t                <label for=\"firstBenefit\">Dental</label>\n\t            </li>\n\t            <li>\n\t                <input type=\"radio\" class=\"inlineSpace\" name=\"benefits\" id=\"secondBenefit\" value=\"Optical\" />\n\t                <label for=\"secondBenefit\">Optical</label>\n\t            </li>\n\t            <li>\n\t                <input type=\"radio\" class=\"inlineSpace\" name=\"benefits\" id=\"thirdBenefit\" value=\"Physiotherapy\" />\n\t                <label for=\"thirdBenefit\">Physiotherapy, osteopathy, chiropractic, acupuncture</label>\n\t            </li>\n\t        </ul>\n\t        <ul>\n\t            <li><strong>How much do you spend a year on Dental?</strong></li>\n\t            <li>\n\t                <input type=\"radio\" class=\"inlineSpace\" name=\"spend\" id=\"rate1a\" value=\"£50\" />\n\t                <label for=\"rate1a\">&pound;50</label>\n\t            </li>\n\t            <li>\n\t                <input type=\"radio\" class=\"inlineSpace\" name=\"spend\" id=\"rate2a\" value=\"£100\" />\n\t                <label for=\"rate2a\">&pound;100</label>\n\t            </li>\n\t            <li>\n\t                <input type=\"radio\" class=\"inlineSpace\" name=\"spend\" id=\"rate3a\" value=\"£150\" />\n\t                <label for=\"rate3a\">&pound;150</label>\n\t            </li>           \n\t        </ul>\n\t        <ul>\n\t            <li><strong>How much do you spend a year on Optical?</strong></li>\n\t            <li>\n\t                <input type=\"radio\" class=\"inlineSpace\" name=\"spend\" id=\"rate1b\" value=\"£50\" />\n\t                <label for=\"rate1a\">&pound;50</label>\n\t            </li>\n\t            <li>\n\t                <input type=\"radio\" class=\"inlineSpace\" name=\"spend\" id=\"rate2b\" value=\"£100\" />\n\t                <label for=\"rate2a\">&pound;100</label>\n\t            </li>\n\t            <li>\n\t                <input type=\"radio\" class=\"inlineSpace\" name=\"spend\" id=\"rate3b\" value=\"£150\" />\n\t                <label for=\"rate3a\">&pound;150</label>\n\t            </li>           \n\t        </ul>\n\t        <ul>\n\t            <li><strong>How much do you spend a year on Physiotherapy, osteopathy, chiropractic, acupuncture?</strong></li>\n\t            <li>\n\t                <input type=\"radio\" class=\"inlineSpace\" name=\"spend\" id=\"rate1c\" value=\"£50\" />\n\t                <label for=\"rate1a\">&pound;50</label>\n\t            </li>\n\t            <li>\n\t                <input type=\"radio\" class=\"inlineSpace\" name=\"spend\" id=\"rate2c\" value=\"£100\" />\n\t                <label for=\"rate2a\">&pound;100</label>\n\t            </li>\n\t            <li>\n\t                <input type=\"radio\" class=\"inlineSpace\" name=\"spend\" id=\"rate3c\" value=\"£150\" />\n\t                <label for=\"rate3a\">&pound;150</label>\n\t            </li>           \n\t        </ul>\n\t        <label class=\"button\"><input type=\"submit\" value=\"View your quote\" class=\"submit\" /></label>\n\t    </div>\n\t\n\nI tried using:\n\n\t$('div.chevron > ul').not($radioClick).hide();\n\t\n\nBut that yielded a bad result where all the lists where hidden.\n\nThanks in advance.",
  "lastActivityDate": "2014-03-17T19:33:59.480",
  "title": "jQuery show hide divs on radio buttons",
  "tags": [
    "javascript",
    "jquery"
  ],
  "docScore": 0,
  "comments": [],
  "answers": [],
  "creationYearMonth": "201403",
  "itemTally": 0,
  "owner": null
}