{"Body":"<ol>\n<li><p>Copyright isn't relevant to this. If any law is involved it will be <em>trademark</em> law. But some genericised trademarks are no longer enforceable.</p></li>\n<li><p>Specific answers for your examples are:</p>\n\n<ol>\n<li>snapable bricks (perhaps. I'm not certain if there is a common generic name for Lego-like toys)</li>\n<li>photocopier. In Australia we never say anything other than photocopier.</li>\n<li>searched the internet for ...</li>\n</ol></li>\n<li><p>Here is a list, though it is incomplete of course: <a href=\"http://en.wikipedia.org/wiki/List_of_generic_and_genericized_trademarks\" rel=\"nofollow\">http://en.wikipedia.org/wiki/List_of_generic_and_genericized_trademarks</a></p></li>\n<li><p>Why are you asking about zero derivations? Only Googled is derived - Lego and Xerox aren't, at least not in the examples you gave.</p></li>\n</ol>\n", "Id":"4638", "ParentId":"4636", "LastEditorUserId":"2555", "CreationDate":"2013-10-07T10:07:16.647", "OwnerUserId":"2555", "PostTypeId":"2", "comments":[], "LastEditDate":"2013-10-07T11:19:59.417", "LastEditedUser":{"UpVotes":"70", "WebsiteUrl":"", "Location":"Australia", "Id":"2555", "DownVotes":"16", "AccountId":"3401915", "Views":"6", "Reputation":"311", "CreationDate":"2013-10-07T08:31:40.093", "DisplayName":"curiousdannii", "LastAccessDate":"2014-01-15T22:35:43.143", "AboutMe":""}, "LastActivityDate":"2013-10-07T11:19:59.417", "Score":"3", "OwnerUser":{"UpVotes":"70", "WebsiteUrl":"", "Location":"Australia", "Id":"2555", "DownVotes":"16", "AccountId":"3401915", "Views":"6", "Reputation":"311", "CreationDate":"2013-10-07T08:31:40.093", "DisplayName":"curiousdannii", "LastAccessDate":"2014-01-15T22:35:43.143", "AboutMe":""}}