{"OwnerUser":{"UpVotes":"15", "DownVotes":"2", "Id":"28", "AccountId":"53332", "Views":"31", "Reputation":"1410", "CreationDate":"2011-09-13T20:55:31.697", "DisplayName":"JoFrhwld", "LastAccessDate":"2013-10-22T11:47:47.293"}, "comments":[], "Body":"<p>It has long been noted that in English, the while the words for many animals are of Germanic etymology, the words for their meats are of French etymology. This must be related to the Norman French invasion of England in 1066, and the usual story goes: the peasants were too poor and oppressed to eat the meat from the animals they raised, because it all went to the French ruling class, and the ruling class never touched the actual animals.</p>\n\n<p>Whether or not the story about <em>why</em> is true, language contact is certainly the culprit.</p>\n\n<p>Notice that for less commonly eaten meats, we just use the name of the animal: <em>bear meat</em>; likewise for meat of North American origin: <em>bison burger</em>.</p>\n", "Id":"561", "ParentId":"553", "CreationDate":"2011-09-27T12:13:45.737", "Score":"15", "PostTypeId":"2", "OwnerUserId":"28", "LastActivityDate":"2011-09-27T12:13:45.737", "CommentCount":"5"}