{"UpVotes":"0", "WebsiteUrl":"http://www.omranic.com", "Id":"1007", "AccountId":"117434", "CreationDate":"2012-05-14T04:01:15.737", "AboutMe":"<p>A proficient multi-skilled software engineer.\nphp, java, c#, .net, apache, mysql, html5, css3, xml, ajax, json, git, svn, ssh, mvc, oop, seo, erp, crm, rest, curl, soap</p>\n\n<ul>\n<li>Personal: Courageous and optimistic Entrepreneur believes he can change the world!</li>\n<li>Professional: 7+ years of experience in software engineering.</li>\n<li>Fields: Web, Mobile, Desktop (respectively), as employer &amp; freelancer.</li>\n<li>Expertise in: Apache, PHP, Java, C# .Net, MySQL, MsSQL, HTML5, CSS3, JS, XML, AJAX, JSON, YAML</li>\n<li>Favor: Quality, over quantity! Following standards &amp; best practices.</li>\n<li>Looking for: interesting software challenges, helping others achieve their needs.</li>\n<li>OS: Windows, Linux, MacOSX, Android</li>\n<li>IDE: Eclipse, Zend Studio, Aptana, Microsoft Visual Studio, Netbeans, PHPStorm</li>\n<li>VCS: Git, Subversion</li>\n<li>Framework : Symfony2, Zend Framework, CodeIgniter, Android sdk, .Net Framework, EXTJS, jquery, Smarty, Doctrine, Twig, YUI, Google APIs</li>\n<li>Webapps: Joomla, Mambo, PHP-Nuke, MKPortal, Pimcore, WordPress, vBulletin, bbPress, MyBB, IPB, phpBB, SMF, XenForo, phpMyAdmin, SQL Buddy, OpenX, osCommerce, Horde, MediaWiki, SugarCRM, Magento, CS-Cart, phpDocumentor, PHPAudit, SPBAS, vCard, 4images, PhotoPost, Xoops, PHPLive, Kayako, Redmine, Drupal</li>\n<li>Keywords: MVC, OOP, ERP, CRM, SEO, Skrill aka Moneybookers, 2checkout, QA, REST, SOAP, cURL, AWS, EC2, S3, DOM, WAMP, LAMP, MAMP, SSH</li>\n<li>Social: G+, Twitter, Facebook, IM, IRC</li>\n</ul>\n", "Age":"27", "Location":"Alexandria, Egypt", "DownVotes":"0", "Views":"0", "Reputation":"101", "DisplayName":"Omranic", "LastAccessDate":"2012-05-14T04:01:15.737"}