{"UpVotes":"1", "WebsiteUrl":"http://www.adameberlin.com/", "Location":"Chicago, IL", "Id":"1351", "DownVotes":"0", "AccountId":"124675", "Views":"0", "Reputation":"101", "CreationDate":"2012-09-26T01:36:12.143", "DisplayName":"Adam Eberlin", "LastAccessDate":"2012-09-26T01:36:12.143", "AboutMe":"<blockquote>\n  <p><strong>Consulting software engineer and interaction designer out of Chicago.</strong></p>\n</blockquote>\n\n<ul>\n<li><p>Careers 2.0: <a href=\"http://careers.stackoverflow.com/aeberlin\">careers.stackoverflow.com/aeberlin</a></p></li>\n<li><p><a href=\"http://www.codefiddle.com/\" rel=\"nofollow\">www.codefiddle.com</a></p></li>\n</ul>\n\n<blockquote>\n  <p>All original source code I post on StackOverflow is licensed under the Stack Overflow community license if a license is not otherwise identified. License information may be available at reference sources, and links to source code elsewhere, including my own, might have their own licenses.</p>\n  \n  <p><em>Use knowledge at your own risk.</em></p>\n</blockquote>\n"}