{"UpVotes":"0", "WebsiteUrl":"http://careers.stackoverflow.com/dfullerton", "Id":"585", "AccountId":"32917", "CreationDate":"2011-12-12T22:20:46.567", "AboutMe":"<p>Stack Exchange <a href=\"http://meta.stackoverflow.com/a/121542/146719\">VP of Engineering</a>.</p>\n\n<p>Formerly:</p>\n\n<ul>\n<li>New York (Careers &amp; Area 51) lead.</li>\n<li>Stack Exchange 1.0 dev lead.</li>\n</ul>\n\n<p>Check out my <a href=\"http://careers.stackoverflow.com/dfullerton\">Careers 2.0 profile</a>.</p>\n\n<p><a href=\"http://hatdash.com/users/3/david-fullerton\" rel=\"nofollow\">I look better with a hat</a>.</p>\n", "Age":"29", "Location":"New York, NY", "DownVotes":"0", "Views":"0", "Reputation":"101", "DisplayName":"David Fullerton", "LastAccessDate":"2013-06-25T21:37:34.383"}