{"UpVotes":"0", "WebsiteUrl":"http://exterraexpeditions.blogspot.com/", "Id":"620", "AccountId":"1021339", "CreationDate":"2011-12-27T00:27:14.470", "AboutMe":"<p>Having been raised by a pair of school teachers, I really enjoy helping others learn. Give me a topic, and I can research and expound for hours.  :-)</p>\n\n<p>I've been working with a group of local authors, both in proofreading and critiquing their works, as well as getting help <em>from</em> them on mine.</p>\n", "Age":"59", "Location":"Sacramento, CA", "DownVotes":"0", "Views":"0", "Reputation":"101", "DisplayName":"WesT", "LastAccessDate":"2011-12-28T03:42:58.357"}