{"UpVotes":"1", "WebsiteUrl":"http://www.tanguay.info/web", "Id":"812", "AccountId":"3237", "CreationDate":"2012-03-03T11:20:20.337", "AboutMe":"<p>web/software developer, .NET, C#, WPF, PHP, software trainer, English teacher, have philosophy degree, love languages, run marathons<br/><br/>\nmy tweets: <a href=\"http://www.twitter.com/edward_tanguay\" rel=\"nofollow\">http://www.twitter.com/edward_tanguay</a>\n<br/><br/>\nmy runs: <a href=\"http://www.tanguay.info/run\" rel=\"nofollow\">http://www.tanguay.info/run</a>\n<br/><br/>\nmy code: <a href=\"http://www.tanguay.info/web\" rel=\"nofollow\">http://www.tanguay.info/web</a>\n<br/><br/>\nmy publications: <a href=\"http://www.video2brain.com/en/products-17.htm#/content?t=2\" rel=\"nofollow\">PHP 5.3 training video (8 hours, video2brain)</a>\n<br/><br/>\nmy projects: <a href=\"http://www.tanguay.info\" rel=\"nofollow\">http://www.tanguay.info</a></p>\n", "Age":"48", "Location":"Berlin, Germany", "DownVotes":"0", "Views":"4", "Reputation":"121", "DisplayName":"Edward Tanguay", "LastAccessDate":"2012-03-05T21:36:03.820"}