{"Body":"<p>I'm pretty interested in historical linguistics, but unfortunately, my school rarely offers the historical linguistics class. What are some go-to resources on historical linguistics, be it books, websites, documentaries, etc? More specifically, I'm looking for historical linguistics in practice; I want to answer the question \"how is it done?\"</p>\n", "Id":"2362", "AcceptedAnswerId":"2371", "Title":"What are the go-to resources on historical linguistics?", "CreationDate":"2012-08-05T23:15:37.653", "AnswerCount":"1", "Tags":"<historical-linguistics><language-change><resources><research>", "PostTypeId":"1", "OwnerUserId":"958", "comments":[], "ViewCount":"210", "LastActivityDate":"2012-08-06T03:41:00.537", "Score":"2", "OwnerUser":{"UpVotes":"40", "WebsiteUrl":"http://labbook.net", "Id":"958", "AccountId":"266116", "CreationDate":"2012-04-26T04:27:19.147", "AboutMe":"<p>I am currently a junior at Penn State pursuing a B.Phil. in Linguistics and a B.S. in Psychology with minors in Arabic and Statistics. I plan to graduate in 2015 to pursue a Ph.D. in linguistics.</p>\n", "Age":"21", "Location":"Pittsburgh, PA", "DownVotes":"2", "Views":"15", "Reputation":"620", "DisplayName":"Nick Anderegg", "LastAccessDate":"2014-01-04T22:11:02.530"}}