{"Body":"<p>Stepping off of the airplane in Lisbon, I could immediately hear that the pronunciation was much different from Brazilian Portuguese, which I am more accustomed to. </p>\n\n<p>The level of vowel deletion was so pronounced in fact, that I almost thought people were speaking Polish, due to the high number of awkward consonant clusters - <em>such as brzydka or ptaki in the Slavic language</em>.</p>\n\n<p>The four most striking and frequent examples I personally heard were:</p>\n\n<ul>\n<li><strong>pessoas</strong> as /ps'oɐʃ/</li>\n<li><strong>português</strong>  as /prt'geʃ/</li>\n<li><strong>Lisboa</strong> as /lʒ'bo,ɐ/</li>\n<li><strong>desculpas</strong> as /dɯ̽ʃ'kuɫps/</li>\n</ul>\n\n<p>Are there any general rules as to which of the vowels are more likely to be deleted?</p>\n", "Id":"4516", "LastEditorUserId":"740", "Title":"What vowels are most likely to be deleted in European Portuguese?", "CreationDate":"2013-09-20T19:47:25.020", "OwnerUserId":"740", "PostTypeId":"1", "Tags":"<vowels><pronunciation><romance-languages><portuguese>", "comments":[], "LastEditDate":"2013-09-20T21:26:40.757", "LastEditedUser":{"UpVotes":"25", "WebsiteUrl":"", "Id":"740", "AccountId":"367785", "CreationDate":"2012-02-05T20:21:08.563", "AboutMe":"", "Age":"29", "Location":"Los Angeles, CA", "DownVotes":"13", "Views":"7", "Reputation":"291", "DisplayName":"Cayetano Gonçalves", "LastAccessDate":"2014-01-18T02:41:09.117"}, "ViewCount":"55", "LastActivityDate":"2013-09-20T21:26:40.757", "Score":"4", "CommentCount":"2", "OwnerUser":{"UpVotes":"25", "WebsiteUrl":"", "Id":"740", "AccountId":"367785", "CreationDate":"2012-02-05T20:21:08.563", "AboutMe":"", "Age":"29", "Location":"Los Angeles, CA", "DownVotes":"13", "Views":"7", "Reputation":"291", "DisplayName":"Cayetano Gonçalves", "LastAccessDate":"2014-01-18T02:41:09.117"}}